color_dom/__init__.py
color_dom/hello.py
color_dom-0.0.2.dist-info/METADATA
color_dom-0.0.2.dist-info/WHEEL
color_dom-0.0.2.dist-info/top_level.txt
color_dom-0.0.2.dist-info/RECORD
